[
    {
        "type": "sourcecred/cli/scores",
        "version": "0.2.0"
    },
    {
        "intervals": [
            {
                "endTimeMs": 1576972800000,
                "startTimeMs": 1576368000000
            },
            {
                "endTimeMs": 1577577600000,
                "startTimeMs": 1576972800000
            },
            {
                "endTimeMs": 1578182400000,
                "startTimeMs": 1577577600000
            },
            {
                "endTimeMs": 1578787200000,
                "startTimeMs": 1578182400000
            },
            {
                "endTimeMs": 1579392000000,
                "startTimeMs": 1578787200000
            },
            {
                "endTimeMs": 1579996800000,
                "startTimeMs": 1579392000000
            },
            {
                "endTimeMs": 1580601600000,
                "startTimeMs": 1579996800000
            },
            {
                "endTimeMs": 1581206400000,
                "startTimeMs": 1580601600000
            },
            {
                "endTimeMs": 1581811200000,
                "startTimeMs": 1581206400000
            },
            {
                "endTimeMs": 1582416000000,
                "startTimeMs": 1581811200000
            },
            {
                "endTimeMs": 1583020800000,
                "startTimeMs": 1582416000000
            },
            {
                "endTimeMs": 1583625600000,
                "startTimeMs": 1583020800000
            },
            {
                "endTimeMs": 1584230400000,
                "startTimeMs": 1583625600000
            },
            {
                "endTimeMs": 1584835200000,
                "startTimeMs": 1584230400000
            },
            {
                "endTimeMs": 1585440000000,
                "startTimeMs": 1584835200000
            }
        ],
        "users": [
            {
                "address": [
                    "sourcecred",
                    "identity",
                    "Ven"
                ],
                "intervalCred": [
                    21.2045938120709,
                    10.602003331179203,
                    8.562533984161881,
                    4.598951673800548,
                    2.8850599387749387,
                    14.989041430300624,
                    7.409930805536688,
                    21.919376452419996,
                    55.37183877127348,
                    27.688211666857658,
                    13.846294159626142,
                    9.411580301079345,
                    41.77428081333611,
                    34.89665118813028,
                    38.376281813355114
                ],
                "totalCred": 313.5366301419029
            },
            {
                "address": [
                    "sourcecred",
                    "identity",
                    "skuhlmann"
                ],
                "intervalCred": [
                    8.295406187929103,
                    4.147996668820796,
                    1.8124660158381176,
                    0.97327795186873,
                    0.6103224687255827,
                    5.204261965747193,
                    2.5718475426295324,
                    1.576016668923732,
                    11.864319172147434,
                    5.932131716547837,
                    2.9660301006032443,
                    21.131795696092862,
                    88.64492923559112,
                    45.79517917142947,
                    79.19667718484179
                ],
                "totalCred": 280.72265774773655
            },
            {
                "address": [
                    "sourcecred",
                    "identity",
                    "hammadj"
                ],
                "intervalCred": [
                    0,
                    0,
                    0,
                    4.711148863904806,
                    4.28178203145742,
                    3.415688098613018,
                    1.7169496203120957,
                    1.0976753755376099,
                    0.5547360950288538,
                    0.27576657212014316,
                    0.13637623035609261,
                    33.86854033609598,
                    33.99201272160921,
                    37.208138528623536,
                    29.313661772566668
                ],
                "totalCred": 150.57247624622545
            },
            {
                "address": [
                    "sourcecred",
                    "identity",
                    "dekanbro"
                ],
                "intervalCred": [
                    0,
                    0,
                    0,
                    0.15412151042591485,
                    1.9415855610420576,
                    3.2503835053391654,
                    2.2721063589622945,
                    1.3685178653953842,
                    0.6892043741439825,
                    0.3439050095023441,
                    0.17126324637293858,
                    9.13788537843651,
                    27.63582335779311,
                    25.38912734270435,
                    41.171524935002026
                ],
                "totalCred": 113.52544844512008
            },
            {
                "address": [
                    "sourcecred",
                    "identity",
                    "YalorMewn"
                ],
                "intervalCred": [
                    0,
                    0,
                    0,
                    0,
                    0,
                    0,
                    0,
                    0,
                    0,
                    0,
                    0,
                    2.7787562172948186,
                    15.820832569798212,
                    23.973011165383998,
                    38.49957538746168
                ],
                "totalCred": 81.07217533993871
            },
            {
                "address": [
                    "sourcecred",
                    "identity",
                    "proofoftom"
                ],
                "intervalCred": [
                    0,
                    0,
                    0,
                    0,
                    0,
                    0,
                    0,
                    0,
                    0,
                    0,
                    0,
                    10.569528286746285,
                    19.268354967810467,
                    18.2954046365041,
                    19.54202286214994
                ],
                "totalCred": 67.67531075321078
            },
            {
                "address": [
                    "sourcecred",
                    "identity",
                    "DarrenRM"
                ],
                "intervalCred": [
                    0,
                    0,
                    0,
                    0,
                    0,
                    0,
                    0,
                    0,
                    0,
                    0,
                    0,
                    11.696851137429462,
                    21.596553201147362,
                    18.563129604031957,
                    12.67021464859398
                ],
                "totalCred": 64.52674859120276
            },
            {
                "address": [
                    "sourcecred",
                    "discord",
                    "MEMBER",
                    "user",
                    "157400886874865664"
                ],
                "intervalCred": [
                    0,
                    0,
                    0,
                    0,
                    0,
                    0,
                    0,
                    0,
                    0,
                    0,
                    0,
                    12.362480158643425,
                    18.93083977577319,
                    8.983637716925603,
                    5.000184272062908
                ],
                "totalCred": 45.277141923405125
            },
            {
                "address": [
                    "sourcecred",
                    "discord",
                    "MEMBER",
                    "user",
                    "442976599139155978"
                ],
                "intervalCred": [
                    0,
                    0,
                    0,
                    0,
                    0,
                    0,
                    0,
                    0,
                    0,
                    0,
                    0,
                    0,
                    20.273505663154072,
                    7.759611358490597,
                    3.968852628490853
                ],
                "totalCred": 32.00196965013552
            },
            {
                "address": [
                    "sourcecred",
                    "discord",
                    "MEMBER",
                    "user",
                    "657069807505637397"
                ],
                "intervalCred": [
                    0,
                    0,
                    0,
                    0,
                    0,
                    0,
                    0,
                    0,
                    0,
                    0,
                    0,
                    0,
                    7.3023920400777955,
                    3.65205143804099,
                    16.129741816352173
                ],
                "totalCred": 27.084185294470956
            },
            {
                "address": [
                    "sourcecred",
                    "discord",
                    "MEMBER",
                    "user",
                    "560581405050929153"
                ],
                "intervalCred": [
                    0,
                    0,
                    0,
                    0,
                    0,
                    0,
                    0,
                    0,
                    0,
                    0,
                    0,
                    0,
                    2.046795843175614,
                    1.9033580725111894,
                    17.6394029143217
                ],
                "totalCred": 21.589556830008505
            },
            {
                "address": [
                    "sourcecred",
                    "discord",
                    "MEMBER",
                    "user",
                    "230856161803501569"
                ],
                "intervalCred": [
                    0,
                    0,
                    0,
                    0,
                    0,
                    0,
                    0,
                    0,
                    0,
                    0,
                    0,
                    3.3650863251264105,
                    1.7885970443186938,
                    1.9438730616368973,
                    14.45117308143722
                ],
                "totalCred": 21.548729512519223
            },
            {
                "address": [
                    "sourcecred",
                    "discord",
                    "MEMBER",
                    "user",
                    "358106929328816129"
                ],
                "intervalCred": [
                    0,
                    0,
                    0,
                    0,
                    0,
                    0,
                    0,
                    0,
                    0,
                    0,
                    0,
                    3.689162357469949,
                    3.8833895765333066,
                    7.7917880440725105,
                    5.22048318632509
                ],
                "totalCred": 20.584823164400856
            },
            {
                "address": [
                    "sourcecred",
                    "discord",
                    "MEMBER",
                    "user",
                    "593095168379453443"
                ],
                "intervalCred": [
                    0,
                    0,
                    0,
                    0,
                    0,
                    0,
                    0,
                    0,
                    0,
                    0,
                    0,
                    1.3015518894401197,
                    7.294641514090379,
                    4.199160141654422,
                    5.404470418580113
                ],
                "totalCred": 18.199823963765034
            },
            {
                "address": [
                    "sourcecred",
                    "discord",
                    "MEMBER",
                    "user",
                    "422890621737500676"
                ],
                "intervalCred": [
                    0,
                    0,
                    0,
                    0,
                    0,
                    0,
                    0,
                    0,
                    0,
                    0,
                    0,
                    8.318995408511483,
                    4.29779599260144,
                    2.2894530393268324,
                    1.2711305982760082
                ],
                "totalCred": 16.177375038715766
            },
            {
                "address": [
                    "sourcecred",
                    "discord",
                    "MEMBER",
                    "user",
                    "471384482126233600"
                ],
                "intervalCred": [
                    0,
                    0,
                    0,
                    0,
                    0,
                    0,
                    0,
                    0,
                    0,
                    0,
                    0,
                    0,
                    7.692598175919344,
                    3.4064185118550907,
                    1.8000228892320072
                ],
                "totalCred": 12.899039577006443
            },
            {
                "address": [
                    "sourcecred",
                    "discord",
                    "MEMBER",
                    "user",
                    "281959219865845761"
                ],
                "intervalCred": [
                    0,
                    0,
                    0,
                    0,
                    0,
                    0,
                    0,
                    0,
                    0,
                    0,
                    0,
                    5.306386163294338,
                    2.7011656209586086,
                    1.2677788531570808,
                    0.6332251381462684
                ],
                "totalCred": 9.908555775556296
            },
            {
                "address": [
                    "sourcecred",
                    "discord",
                    "MEMBER",
                    "user",
                    "679156502220636200"
                ],
                "intervalCred": [
                    0,
                    0,
                    0,
                    0,
                    0,
                    0,
                    0,
                    0,
                    0,
                    0,
                    0,
                    0,
                    3.8505760105519036,
                    3.345150669473252,
                    1.5859217302996074
                ],
                "totalCred": 8.781648410324763
            },
            {
                "address": [
                    "sourcecred",
                    "discord",
                    "MEMBER",
                    "user",
                    "466680100553883659"
                ],
                "intervalCred": [
                    0,
                    0,
                    0,
                    0,
                    0,
                    0,
                    0,
                    0,
                    0,
                    0,
                    0,
                    0,
                    0,
                    0,
                    8.106672458028878
                ],
                "totalCred": 8.106672458028878
            },
            {
                "address": [
                    "sourcecred",
                    "discord",
                    "MEMBER",
                    "user",
                    "428482726421856257"
                ],
                "intervalCred": [
                    0,
                    0,
                    0,
                    0,
                    0,
                    0,
                    0,
                    0,
                    0,
                    0,
                    0,
                    4.12774922360815,
                    2.1503121638897573,
                    1.0872868317573334,
                    0.5564393320616421
                ],
                "totalCred": 7.921787551316883
            },
            {
                "address": [
                    "sourcecred",
                    "discord",
                    "MEMBER",
                    "user",
                    "186994498352578563"
                ],
                "intervalCred": [
                    0,
                    0,
                    0,
                    0,
                    0,
                    0,
                    0,
                    0,
                    0,
                    0,
                    0,
                    1.2788720565138756,
                    3.7666368699699224,
                    1.7280502498681436,
                    0.7980041095622166
                ],
                "totalCred": 7.571563285914158
            },
            {
                "address": [
                    "sourcecred",
                    "discord",
                    "MEMBER",
                    "user",
                    "459085466239631371"
                ],
                "intervalCred": [
                    0,
                    0,
                    0,
                    0,
                    0,
                    0,
                    0,
                    0,
                    0,
                    0,
                    0,
                    0.06240411051177147,
                    1.8165436861589228,
                    0.8732662299608073,
                    2.464307520193382
                ],
                "totalCred": 5.216521546824883
            },
            {
                "address": [
                    "sourcecred",
                    "discord",
                    "MEMBER",
                    "user",
                    "184804183965302785"
                ],
                "intervalCred": [
                    0,
                    0,
                    0,
                    0,
                    0,
                    0,
                    0,
                    0,
                    0,
                    0,
                    0,
                    0.015010152775411132,
                    0.07887900118689553,
                    1.7593776218486785,
                    2.3339328936123374
                ],
                "totalCred": 4.187199669423323
            },
            {
                "address": [
                    "sourcecred",
                    "discord",
                    "MEMBER",
                    "user",
                    "368363326524227584"
                ],
                "intervalCred": [
                    0,
                    0,
                    0,
                    0,
                    0,
                    0,
                    0,
                    0,
                    0,
                    0,
                    0,
                    0,
                    2.2901043945927,
                    1.1090345273092008,
                    0.5202018345624799
                ],
                "totalCred": 3.919340756464381
            },
            {
                "address": [
                    "sourcecred",
                    "discord",
                    "MEMBER",
                    "user",
                    "347835144926658568"
                ],
                "intervalCred": [
                    0,
                    0,
                    0,
                    0,
                    0,
                    0,
                    0,
                    0,
                    0,
                    0,
                    0,
                    0,
                    0.1834910447386598,
                    0.16304681664942827,
                    3.5250839631661743
                ],
                "totalCred": 3.8716218245542624
            },
            {
                "address": [
                    "sourcecred",
                    "github",
                    "USERLIKE",
                    "USER",
                    "burrrata"
                ],
                "intervalCred": [
                    0,
                    0,
                    0,
                    0,
                    0,
                    0,
                    0,
                    0,
                    0,
                    0,
                    0,
                    1.642038468470427,
                    1.191876291458972,
                    0.5765131833128287,
                    0.23979328648191606
                ],
                "totalCred": 3.650221229724144
            },
            {
                "address": [
                    "sourcecred",
                    "discord",
                    "MEMBER",
                    "bot",
                    "689581797574574087"
                ],
                "intervalCred": [
                    0,
                    0,
                    0,
                    0,
                    0,
                    0,
                    0,
                    0,
                    0,
                    0,
                    0,
                    0,
                    0,
                    1.8888544707773283,
                    1.1078302197321857
                ],
                "totalCred": 2.9966846905095137
            },
            {
                "address": [
                    "sourcecred",
                    "github",
                    "USERLIKE",
                    "USER",
                    "arsena21"
                ],
                "intervalCred": [
                    0,
                    0,
                    0,
                    0,
                    0,
                    0,
                    0,
                    0,
                    0,
                    0,
                    0,
                    0,
                    0,
                    0,
                    2.2853334664479132
                ],
                "totalCred": 2.2853334664479132
            },
            {
                "address": [
                    "sourcecred",
                    "discord",
                    "MEMBER",
                    "user",
                    "505789102222737420"
                ],
                "intervalCred": [
                    0,
                    0,
                    0,
                    0,
                    0,
                    0,
                    0,
                    0,
                    0,
                    0,
                    0,
                    0.2202385506913309,
                    0.43102839847802255,
                    0.4942153042783272,
                    0.2411387017744669
                ],
                "totalCred": 1.3866209552221476
            },
            {
                "address": [
                    "sourcecred",
                    "discord",
                    "MEMBER",
                    "user",
                    "187076806413778944"
                ],
                "intervalCred": [
                    0,
                    0,
                    0,
                    0,
                    0,
                    0,
                    0,
                    0,
                    0,
                    0,
                    0,
                    0,
                    0.6887321371931063,
                    0.33326102757843123,
                    0.17637826418805216
                ],
                "totalCred": 1.1983714289595897
            },
            {
                "address": [
                    "sourcecred",
                    "discord",
                    "MEMBER",
                    "user",
                    "566540150641786890"
                ],
                "intervalCred": [
                    0,
                    0,
                    0,
                    0,
                    0,
                    0,
                    0,
                    0,
                    0,
                    0,
                    0,
                    0,
                    0,
                    0.6604602676025747,
                    0.5330208062267925
                ],
                "totalCred": 1.1934810738293673
            },
            {
                "address": [
                    "sourcecred",
                    "discord",
                    "MEMBER",
                    "user",
                    "507972449132871681"
                ],
                "intervalCred": [
                    0,
                    0,
                    0,
                    0,
                    0,
                    0,
                    0,
                    0,
                    0,
                    0,
                    0,
                    0,
                    0.22305448153289728,
                    0.6120138245880322,
                    0.20019752338468094
                ],
                "totalCred": 1.0352658295056105
            },
            {
                "address": [
                    "sourcecred",
                    "discord",
                    "MEMBER",
                    "user",
                    "680500168864563253"
                ],
                "intervalCred": [
                    0,
                    0,
                    0,
                    0,
                    0,
                    0,
                    0,
                    0,
                    0,
                    0,
                    0,
                    0.1644950178181668,
                    0.29463280365141575,
                    0.22714318908050238,
                    0.10359416414006561
                ],
                "totalCred": 0.7898651746901505
            },
            {
                "address": [
                    "sourcecred",
                    "discord",
                    "MEMBER",
                    "user",
                    "621474267988623393"
                ],
                "intervalCred": [
                    0,
                    0,
                    0,
                    0,
                    0,
                    0,
                    0,
                    0,
                    0,
                    0,
                    0,
                    0,
                    0.4075043153565467,
                    0.24813753842381706,
                    0.12031530901527111
                ],
                "totalCred": 0.7759571627956349
            },
            {
                "address": [
                    "sourcecred",
                    "discord",
                    "MEMBER",
                    "user",
                    "313822952003076108"
                ],
                "intervalCred": [
                    0,
                    0,
                    0,
                    0,
                    0,
                    0,
                    0,
                    0,
                    0,
                    0,
                    0,
                    0,
                    0.04580648349946504,
                    0.09922933907035524,
                    0.5805175168547592
                ],
                "totalCred": 0.7255533394245794
            },
            {
                "address": [
                    "sourcecred",
                    "discord",
                    "MEMBER",
                    "user",
                    "436039211335024640"
                ],
                "intervalCred": [
                    0,
                    0,
                    0,
                    0,
                    0,
                    0,
                    0,
                    0,
                    0,
                    0,
                    0,
                    0.18093657306115393,
                    0.2907782562073039,
                    0.12949925163715656,
                    0.07586273619027942
                ],
                "totalCred": 0.6770768170958938
            },
            {
                "address": [
                    "sourcecred",
                    "discord",
                    "MEMBER",
                    "user",
                    "370936911268806667"
                ],
                "intervalCred": [
                    0,
                    0,
                    0,
                    0,
                    0,
                    0,
                    0,
                    0,
                    0,
                    0,
                    0,
                    0.30430349297358944,
                    0.20317627192043036,
                    0.10787505942862685,
                    0.04809645418029278
                ],
                "totalCred": 0.6634512785029394
            },
            {
                "address": [
                    "sourcecred",
                    "discord",
                    "MEMBER",
                    "user",
                    "443527705250758696"
                ],
                "intervalCred": [
                    0,
                    0,
                    0,
                    0,
                    0,
                    0,
                    0,
                    0,
                    0,
                    0,
                    0,
                    0.06427461545349404,
                    0.36974586903119055,
                    0.11593165401230002,
                    0.05884558542562031
                ],
                "totalCred": 0.608797723922605
            },
            {
                "address": [
                    "sourcecred",
                    "discord",
                    "MEMBER",
                    "user",
                    "208321561982271489"
                ],
                "intervalCred": [
                    0,
                    0,
                    0,
                    0,
                    0,
                    0,
                    0,
                    0,
                    0,
                    0,
                    0,
                    0,
                    0.16257567689182015,
                    0.08405929218197944,
                    0.2952419787162207
                ],
                "totalCred": 0.5418769477900203
            },
            {
                "address": [
                    "sourcecred",
                    "discord",
                    "MEMBER",
                    "user",
                    "620872701745299457"
                ],
                "intervalCred": [
                    0,
                    0,
                    0,
                    0,
                    0,
                    0,
                    0,
                    0,
                    0,
                    0,
                    0,
                    0,
                    0.22636896785866809,
                    0.1991648829790138,
                    0.0919387879128315
                ],
                "totalCred": 0.5174726387505134
            },
            {
                "address": [
                    "sourcecred",
                    "discord",
                    "MEMBER",
                    "user",
                    "529915588454121474"
                ],
                "intervalCred": [
                    0,
                    0,
                    0,
                    0,
                    0,
                    0,
                    0,
                    0,
                    0,
                    0,
                    0,
                    0,
                    0.2812311294497148,
                    0.13785159778644676,
                    0.07384740753017743
                ],
                "totalCred": 0.492930134766339
            },
            {
                "address": [
                    "sourcecred",
                    "github",
                    "USERLIKE",
                    "USER",
                    "ahoffaxiom"
                ],
                "intervalCred": [
                    0,
                    0,
                    0,
                    0,
                    0,
                    0,
                    0.2088531725593885,
                    0.12825738772327744,
                    0.06482346240624262,
                    0.03244597247201318,
                    0.01626673179158416,
                    0.008547682189256636,
                    0.004202796176961125,
                    0.002892859451866079,
                    0.00118892890152715
                ],
                "totalCred": 0.46747899367211687
            },
            {
                "address": [
                    "sourcecred",
                    "github",
                    "USERLIKE",
                    "USER",
                    "nsward"
                ],
                "intervalCred": [
                    0,
                    0,
                    0,
                    0,
                    0,
                    0,
                    0,
                    0,
                    0,
                    0,
                    0,
                    0,
                    0.25474097610427854,
                    0.1302239751207259,
                    0.06589770580200317
                ],
                "totalCred": 0.45086265702700756
            },
            {
                "address": [
                    "sourcecred",
                    "discord",
                    "MEMBER",
                    "user",
                    "513394497850179629"
                ],
                "intervalCred": [
                    0,
                    0,
                    0,
                    0,
                    0,
                    0,
                    0,
                    0,
                    0,
                    0,
                    0,
                    0,
                    0.04580648349946504,
                    0.022896058220944145,
                    0.36366300187580247
                ],
                "totalCred": 0.43236554359621165
            },
            {
                "address": [
                    "sourcecred",
                    "discord",
                    "MEMBER",
                    "user",
                    "403238566769065985"
                ],
                "intervalCred": [
                    0,
                    0,
                    0,
                    0,
                    0,
                    0,
                    0,
                    0,
                    0,
                    0,
                    0,
                    0.06064563464737898,
                    0.08174499410048476,
                    0.18882121171674834,
                    0.09947091626924319
                ],
                "totalCred": 0.43068275673385525
            },
            {
                "address": [
                    "sourcecred",
                    "discord",
                    "MEMBER",
                    "user",
                    "468883290577960980"
                ],
                "intervalCred": [
                    0,
                    0,
                    0,
                    0,
                    0,
                    0,
                    0,
                    0,
                    0,
                    0,
                    0,
                    0,
                    0,
                    0,
                    0.12963225456456734
                ],
                "totalCred": 0.12963225456456734
            },
            {
                "address": [
                    "sourcecred",
                    "github",
                    "USERLIKE",
                    "USER",
                    "pcowgill"
                ],
                "intervalCred": [
                    0,
                    0,
                    0,
                    0,
                    0,
                    0,
                    0,
                    0,
                    0,
                    0,
                    0,
                    0,
                    0,
                    0,
                    0
                ],
                "totalCred": 0
            }
        ]
    }
]
